{
  "dataset": "DAUB",
  "network": "sstnet",
  "train_script_override": "",
  "train_model_path": "",
  "train_output_root": "logs",
  "optimizer_type": "",
  "init_lr": "",
  "min_lr": "",
  "momentum": "",
  "weight_decay": "",
  "eval_period": 10,
  "eval_confidence": 0.001,
  "eval_nms_iou": 0.6,
  "eval_json_path": "",
  "eval_image_root": "",
  "train_txt_path": "",
  "val_txt_path": "",
  "acm_image_root": "",
  "acm_base_size": 512,
  "acm_batch_size": 4,
  "acm_epochs": 100,
  "acm_warm_up_epochs": 0,
  "acm_num_classes": 1,
  "acm_stride": 8,
  "acm_num_workers": 2,
  "acm_save_every": 10,
  "acm_run_name": "",
  "acm_ema": "",
  "acm_freeze_train": "",
  "acm_freeze_epochs": "",
  "acm_lr_decay_type": "",
  "acm_eval_flag": true,
  "acm_eval_period": 10,
  "acm_eval_json_path": "",
  "acm_eval_image_root": "",
  "dna_base_size": 512,
  "dna_base_size_by_dataset": {
    "DAUB": 512,
    "IRDST": 512,
    "ITSDT_15K": 512
  },
  "dna_batch_size_by_dataset": {
    "DAUB": 4
  },
  "dataset_root_prefix": "",
  "alc_image_root": "",
  "alc_base_size": 512,
  "alc_batch_size": 4,
  "alc_epochs": 100,
  "alc_warm_up_epochs": 0,
  "alc_num_classes": 1,
  "alc_stride": 8,
  "alc_num_workers": 2,
  "alc_save_every": 10,
  "alc_run_name": "",
  "alc_mosaic": true,
  "alc_mixup": true,
  "alc_det_mode": "",
  "alc_eval_flag": true,
  "alc_eval_period": 10,
  "alc_eval_json_path": "",
  "alc_eval_image_root": "",
  "uiu_batch_size": 2,
  "uiu_det_mode": "",
  "uiu_stride": "8",
  "dna_stride": 8,
  "uiu_fp16": false,
  "sctrans_image_root": "",
  "sctrans_base_size": 512,
  "sctrans_batch_size": 4,
  "sctrans_epochs": 100,
  "sctrans_warm_up_epochs": 0,
  "sctrans_num_classes": 1,
  "sctrans_stride": 8,
  "sctrans_num_workers": 2,
  "sctrans_save_every": 10,
  "sctrans_mosaic": true,
  "sctrans_mixup": true,
  "sctrans_eval_flag": true,
  "sctrans_eval_period": 10,
  "sctrans_eval_json_path": "",
  "sctrans_eval_image_root": ""
}
